Metadata-Version: 1.0
Name: cmdline-chipmunk
Version: 0.2.0
Summary: Python command line application bare bones template.
Home-page: http://gehrcke.de/2014/02/distributing-a-python-command-line-application
Author: Xiangyu_Gao
Author-email: xg673@nyu.edu
License: UNKNOWN
Platform: UNKNOWN
